README.md
requirements.txt
setup.py
proba_lib/__init__.py
proba_lib/base.py
proba_lib.egg-info/PKG-INFO
proba_lib.egg-info/SOURCES.txt
proba_lib.egg-info/dependency_links.txt
proba_lib.egg-info/not-zip-safe
proba_lib.egg-info/top_level.txt
proba_lib/events/__init__.py
proba_lib/operations/__init__.py
proba_lib/operations/probabily_table.py