Metadata-Version: 1.0
Name: proba-lib
Version: 0.0.1
Summary: simple probality library
Home-page: UNKNOWN
Author: Dimitri Korsch
Author-email: korschdima@gmail.com
License: MIT License
Platform: UNKNOWN
